knxdclient/__init__.py
knxdclient/client.py
knxdclient/encoding.py
knxdclient/packets.py
knxdclient/py.typed
knxdclient-1.2.0.dist-info/LICENSE
knxdclient-1.2.0.dist-info/METADATA
knxdclient-1.2.0.dist-info/WHEEL
knxdclient-1.2.0.dist-info/top_level.txt
knxdclient-1.2.0.dist-info/RECORD
