Metadata-Version: 2.2
Name: knxdclient
Version: 1.2.0
Summary: A pure Python async client for KNXD's (EIBD's) native Layer 4
Home-page: https://github.com/mhthies/knxdclient
Author: Michael Thies
Author-email: mail@mhthies.de
License: Apache License 2.0
Classifier: Programming Language :: Python :: 3
Classifier: License :: OSI Approved :: Apache Software License
Classifier: Operating System :: OS Independent
Classifier: Development Status :: 5 - Production/Stable
Requires-Python: >=3.7
License-File: LICENSE
